vectorizedsampleentropy
