Metadata-Version: 1.1
Name: vectorizedsampleentropy
Version: 0.0.3.post1
Summary: Vectorized implementations of sample entropy (SampEn) and approximate entropy (ApEn)
Home-page: https://github.com/kirahg/vectorized-sample-entropy
Author: Kira Huselius Gylling
Author-email: kira.gylling@gmail.com
License: GPL 3.0
Download-URL: https://github.com/kirahg/vectorized-sample-entropy/tarball/0.0.3-1
Keywords: entropy,data,statistics,time series
Platform: UNKNOWN
